dataguard/__init__.py
dataguard/checks.py
dataguard/cli.py
dataguard/core.py
dataguard/report.py
dataguard/roles.py
dataguard/signal.py
dataguard_lite-0.4.0.dist-info/licenses/LICENSE
dataguard_lite-0.4.0.dist-info/METADATA
dataguard_lite-0.4.0.dist-info/WHEEL
dataguard_lite-0.4.0.dist-info/entry_points.txt
dataguard_lite-0.4.0.dist-info/top_level.txt
dataguard_lite-0.4.0.dist-info/RECORD
