Metadata-Version: 2.4
Name: dataguard-lite
Version: 0.4.0
Summary: Lightweight dataset quality checks for CSV files
Author: Aditya Kinikar
License: MIT
Classifier: Programming Language :: Python :: 3
Classifier: License :: OSI Approved :: MIT License
Requires-Python: >=3.8
License-File: LICENSE
Requires-Dist: pandas
Dynamic: license-file
